LICENSE
MANIFEST.in
README.md
setup.py
django_top_notify/__init__.py
django_top_notify/admin.py
django_top_notify/apps.py
django_top_notify/constants.py
django_top_notify/models.py
django_top_notify/tests.py
django_top_notify/urls.py
django_top_notify/views.py
django_top_notify.egg-info/PKG-INFO
django_top_notify.egg-info/SOURCES.txt
django_top_notify.egg-info/dependency_links.txt
django_top_notify.egg-info/not-zip-safe
django_top_notify.egg-info/top_level.txt
django_top_notify/migrations/0001_initial.py
django_top_notify/migrations/__init__.py
docs/pics/alert_top_notification.png
docs/pics/configuration.png
docs/pics/hint_top_notification.png