Metadata-Version: 2.1
Name: django-top-notify
Version: 1.0.0
Summary: A top notification bar based on Django project
Home-page: https://github.com/normal-wls/django-top-notify
Author: waylon
Author-email: 1158341873@qq.com
License: UNKNOWN
Platform: UNKNOWN
License-File: LICENSE
